{
  "pages": [
    {
      "multi": true,
      "content": [
        {
          "Column": {
            "mainAxisSize": "min",
            "mainAxisAlignment": "start",
            "crossAxisAlignment": "start",
            "children": [
              {
                "Text": {
                  "text": "Horizontal"
                }
              },
              {
                "Row": {
                  "children": [
                    {
                      "Flexible": {
                        "flex": 3,
                        "child": {
                          "Placeholder": {
                            "fallbackHeight": 30
                          }
                        }
                      }
                    },
                    {
                      "Spacer": {
                        "flex": 1
                      }
                    },
                    {
                      "Flexible": {
                        "flex": 2,
                        "child": {
                          "Placeholder": {
                            "fallbackHeight": 30
                          }
                        }
                      }
                    }
                  ]
                }
              }
            ]
          }
        },
        {
          "SizedBox": {
            "height": 10
          }
        },
        {
          "Text": {
            "text": "Vertikal"
          }
        },
        {
          "Container": {
            "color": "EEEEEE",
            "height": 100,
            "child": {
              "Column": {
                "children": [
                  {
                    "Flexible": {
                      "flex": 3,
                      "child": {
                        "Placeholder": {
                          "fallbackHeight": 30
                        }
                      }
                    }
                  },
                  {
                    "Spacer": {
                      "flex": 1
                    }
                  },
                  {
                    "Flexible": {
                      "flex": 2,
                      "child": {
                        "Placeholder": {
                          "fallbackHeight": 30
                        }
                      }
                    }
                  }
                ]
              }
            }
          }
        }
      ]
    }
  ]
}